caactus/__init__.py
caactus/background_processing.py
caactus/csv_summary.py
caactus/pln_modelling.py
caactus/renaming.py
caactus/summary_statistics.py
caactus/summary_statistics_eucast.py
caactus/tif2h5py.py
caactus/__pycache__/__init__.cpython-310.pyc
caactus/__pycache__/background_processing.cpython-310.pyc
caactus/__pycache__/pln_modelling.cpython-310.pyc
caactus/__pycache__/summary_statistics.cpython-310.pyc
caactus/__pycache__/tif2h5py.cpython-310.pyc
caactus-0.1.8.dist-info/licenses/LICENSE
caactus-0.1.8.dist-info/METADATA
caactus-0.1.8.dist-info/WHEEL
caactus-0.1.8.dist-info/entry_points.txt
caactus-0.1.8.dist-info/top_level.txt
caactus-0.1.8.dist-info/RECORD
