Metadata-Version: 2.4
Name: caactus
Version: 0.1.8
Summary: Package for pre- and post-processing of images and data for working with ilastik-software
Author-email: Jakob Scheler <jakobscheler@gmail.com>
Maintainer-email: Jakob Scheler <jakobscheler@gmail.com>
License: MIT License
Project-URL: Repository, https://github.com/mr2raccoon/caactus
Project-URL: Documentation, https://github.com/mr2raccoon/caactus
Keywords: python,count,data,ilastik,image data,image processing,PLN,image analysis
Classifier: Development Status :: 4 - Beta
Classifier: Intended Audience :: Science/Research
Classifier: License :: OSI Approved :: MIT License
Classifier: Programming Language :: Python
Requires-Python: >=3.10.12
License-File: LICENSE
Requires-Dist: imagecodecs
Requires-Dist: tifffile
Requires-Dist: h5py
Requires-Dist: numpy
Requires-Dist: pathlib
Requires-Dist: pandas
Requires-Dist: matplotlib
Requires-Dist: pyPLNmodels
Requires-Dist: tomli
Requires-Dist: argparse
Requires-Dist: seaborn
Dynamic: license-file
